setup.py
Rudp/Event.py
Rudp/Logging.py
Rudp/Rudp.py
Rudp/__init__.py
Rudp/vsftp.py
Rudp/examples/RudpReceiver.py
Rudp/examples/RudpSender.py
Rudp/examples/__init__.py
Rudp/test/RudpSenderTest.py
Rudp/test/__init__.py
Rudp/test/vsftp_test.py
python_rudp.egg-info/PKG-INFO
python_rudp.egg-info/SOURCES.txt
python_rudp.egg-info/dependency_links.txt
python_rudp.egg-info/top_level.txt