Metadata-Version: 1.1
Name: python-rudp
Version: 1.0.1
Summary: A rUDP library for Python
Home-page: https://github.com/hoffmabc/python-rudp
Author: Brian Hoffman
Author-email: brian@openbazaar.org
License: MIT
Keywords: udp rudp networking p2p
Platform: UNKNOWN
Classifier: Development Status :: 3 - Alpha
Classifier: Intended Audience :: Developers
Classifier: Topic :: Software Development :: Libraries
Classifier: License :: OSI Approved :: MIT License
Classifier: Programming Language :: Python :: 2.7
Classifier: Programming Language :: Python :: 3
Classifier: Programming Language :: Python :: 3.2
Classifier: Programming Language :: Python :: 3.3
Classifier: Programming Language :: Python :: 3.4
